lndoctor/__init__.py
lndoctor/_version.py
lndoctor/cli/__init__.py
lndoctor/cli/lndoctor.py
lndoctor-0.1.0.dist-info/LICENSE
lndoctor-0.1.0.dist-info/METADATA
lndoctor-0.1.0.dist-info/WHEEL
lndoctor-0.1.0.dist-info/entry_points.txt
lndoctor-0.1.0.dist-info/top_level.txt
lndoctor-0.1.0.dist-info/RECORD
